biobuilder/__init__.py
biobuilder/coverageTest.py
biobuilder/exceptions.py
biobuilder/system.py
biobuilder/topology.py
biobuilder/builder/__init__.py
biobuilder/builder/builder.py
biobuilder/builder/proteinBuilder.py
biobuilder/builder/solutionBuilder.py
biobuilder/element/__init__.py
biobuilder/element/atom.py
biobuilder/element/chain.py
biobuilder/element/molecule.py
biobuilder/tests/__init__.py
biobuilder/tests/conftest.py
biobuilder/tests/test_baseDimension.py
biobuilder/tests/test_judgement.py
biobuilder/tests/test_locate.py
biobuilder/tests/test_quantity.py
biobuilder/tests/test_unique.py
biobuilder/tests/test_unit.py
biobuilder/tests/test_unitDefinition.py
biobuilder/unit/__init__.py
biobuilder/unit/baseDimension.py
biobuilder/unit/quantity.py
biobuilder/unit/unit.py
biobuilder/unit/unitDefinition.py
biobuilder/utils/__init__.py
biobuilder/utils/judgement.py
biobuilder/utils/locate.py
biobuilder/utils/unique.py
biobuilder/writer/__init__.py
biobuilder/writer/pdbWriter.py
biobuilder-0.1.0.dist-info/LICENSE
biobuilder-0.1.0.dist-info/METADATA
biobuilder-0.1.0.dist-info/WHEEL
biobuilder-0.1.0.dist-info/top_level.txt
biobuilder-0.1.0.dist-info/RECORD
